<?xml version="1.0" encoding="UTF-8"?>
<office:document-content xmlns:office="urn:oasis:names:tc:opendocument:xmlns:office:1.0" xmlns:style="urn:oasis:names:tc:opendocument:xmlns:style:1.0" xmlns:text="urn:oasis:names:tc:opendocument:xmlns:text:1.0" xmlns:table="urn:oasis:names:tc:opendocument:xmlns:table:1.0" xmlns:draw="urn:oasis:names:tc:opendocument:xmlns:drawing:1.0" xmlns:fo="urn:oasis:names:tc:opendocument:xmlns:xsl-fo-compatible:1.0" xmlns:xlink="http://www.w3.org/1999/xlink" xmlns:dc="http://purl.org/dc/elements/1.1/" xmlns:meta="urn:oasis:names:tc:opendocument:xmlns:meta:1.0" xmlns:number="urn:oasis:names:tc:opendocument:xmlns:datastyle:1.0" xmlns:svg="urn:oasis:names:tc:opendocument:xmlns:svg-compatible:1.0" xmlns:chart="urn:oasis:names:tc:opendocument:xmlns:chart:1.0" xmlns:dr3d="urn:oasis:names:tc:opendocument:xmlns:dr3d:1.0" xmlns:math="http://www.w3.org/1998/Math/MathML" xmlns:form="urn:oasis:names:tc:opendocument:xmlns:form:1.0" xmlns:script="urn:oasis:names:tc:opendocument:xmlns:script:1.0" xmlns:ooo="http://openoffice.org/2004/office" xmlns:ooow="http://openoffice.org/2004/writer" xmlns:oooc="http://openoffice.org/2004/calc" xmlns:dom="http://www.w3.org/2001/xml-events" xmlns:xforms="http://www.w3.org/2002/xforms" xmlns:xsd="http://www.w3.org/2001/XMLSchema" xmlns:xsi="http://www.w3.org/2001/XMLSchema-instance" xmlns:rpt="http://openoffice.org/2005/report" xmlns:of="urn:oasis:names:tc:opendocument:xmlns:of:1.2" xmlns:xhtml="http://www.w3.org/1999/xhtml" xmlns:grddl="http://www.w3.org/2003/g/data-view#" xmlns:officeooo="http://openoffice.org/2009/office" xmlns:tableooo="http://openoffice.org/2009/table" xmlns:drawooo="http://openoffice.org/2010/draw" xmlns:calcext="urn:org:documentfoundation:names:experimental:calc:xmlns:calcext:1.0" xmlns:loext="urn:org:documentfoundation:names:experimental:office:xmlns:loext:1.0" xmlns:field="urn:openoffice:names:experimental:ooo-ms-interop:xmlns:field:1.0" xmlns:formx="urn:openoffice:names:experimental:ooxml-odf-interop:xmlns:form:1.0" xmlns:css3t="http://www.w3.org/TR/css3-text/" office:version="1.2"><office:scripts/><office:font-face-decls><style:font-face style:name="Arial" svg:font-family="Arial" style:font-family-generic="roman" style:font-pitch="variable"/><style:font-face style:name="Georgia" svg:font-family="Georgia" style:font-family-generic="roman" style:font-pitch="variable"/><style:font-face style:name="Liberation Sans" svg:font-family="&apos;Liberation Sans&apos;" style:font-family-generic="swiss" style:font-pitch="variable"/><style:font-face style:name="Arial1" svg:font-family="Arial" style:font-family-generic="system" style:font-pitch="variable"/><style:font-face style:name="Georgia1" svg:font-family="Georgia" style:font-family-generic="system" style:font-pitch="variable"/><style:font-face style:name="Linux Libertine G" svg:font-family="&apos;Linux Libertine G&apos;" style:font-family-generic="system" style:font-pitch="variable"/></office:font-face-decls><office:automatic-styles><style:style style:name="P1" style:family="paragraph" style:parent-style-name="Standard"><style:paragraph-properties fo:break-before="auto" fo:break-after="auto" fo:padding="0in" fo:border="none"/></style:style><style:style style:name="P2" style:family="paragraph" style:parent-style-name="Standard"><style:paragraph-properties fo:margin-top="0in" fo:margin-bottom="0.1563in" loext:contextual-spacing="false" fo:line-height="100%" fo:break-before="auto" fo:break-after="auto" fo:padding="0in" fo:border="none"/></style:style><style:style style:name="P3" style:family="paragraph" style:parent-style-name="Standard" style:master-page-name="Standard"><style:paragraph-properties style:page-number="1" fo:break-before="auto" fo:break-after="auto" fo:padding="0in" fo:border="none"/></style:style><style:style style:name="P4" style:family="paragraph" style:parent-style-name="Heading_20_2"><style:paragraph-properties fo:margin-top="0in" fo:margin-bottom="0.1563in" loext:contextual-spacing="false" fo:line-height="100%" fo:break-before="auto" fo:break-after="auto" fo:padding="0in" fo:border="none"/></style:style><style:style style:name="T1" style:family="text"><style:text-properties fo:font-style="italic" style:font-style-asian="italic"/></style:style><style:style style:name="T2" style:family="text"><style:text-properties fo:font-weight="bold" style:font-weight-asian="bold"/></style:style><style:style style:name="T3" style:family="text"><style:text-properties fo:color="#1155cc" style:text-underline-style="solid" style:text-underline-width="auto" style:text-underline-color="font-color"/></style:style><style:style style:name="fr1" style:family="graphic" style:parent-style-name="Graphics"><style:graphic-properties fo:margin-left="0in" fo:margin-right="0in" fo:margin-top="0in" fo:margin-bottom="0in" fo:background-color="transparent" draw:fill="none" draw:fill-color="#ffffff" fo:padding="0in" fo:border="none" style:mirror="none" fo:clip="rect(0in, 0in, 0in, 0in)" draw:luminance="0%" draw:contrast="0%" draw:red="0%" draw:green="0%" draw:blue="0%" draw:gamma="100%" draw:color-inversion="false" draw:image-opacity="100%" draw:color-mode="standard"/></style:style></office:automatic-styles><office:body><office:text><text:sequence-decls><text:sequence-decl text:display-outline-level="0" text:name="Illustration"/><text:sequence-decl text:display-outline-level="0" text:name="Table"/><text:sequence-decl text:display-outline-level="0" text:name="Text"/><text:sequence-decl text:display-outline-level="0" text:name="Drawing"/></text:sequence-decls><text:p text:style-name="P3">In the patient’s ‘Summary’ chart tab is a portlet named <text:span text:style-name="T1">Warnings/Alerts</text:span> where you will see drug interaction warnings, allergy warnings, duplicate therapy alerts, guidelines (scripted rules) etc. for the patient.</text:p><text:p text:style-name="P1"><draw:frame draw:style-name="fr1" draw:name="image9.png" text:anchor-type="as-char" svg:width="4.6146in" svg:height="2.552in" draw:z-index="0"><draw:image xlink:href="Pictures/10000000000001BB000000F5CA0B5C9044D46272.png" xlink:type="simple" xlink:show="embed" xlink:actuate="onLoad" loext:mime-type="image/png"/></draw:frame></text:p><text:p text:style-name="P1">Also, as a separate chart tab in the patient’s chart, is a chart tab named ‘Warnings’, you will see drug interaction warnings, allergy warnings, duplicate therapy alerts, etc. for the patient.</text:p><text:p text:style-name="P1"><draw:frame draw:style-name="fr1" draw:name="image3.png" text:anchor-type="as-char" svg:width="9.4374in" svg:height="5.4374in" draw:z-index="0"><draw:image xlink:href="Pictures/100000000000038A0000020A63F8B6A4131A498C.png" xlink:type="simple" xlink:show="embed" xlink:actuate="onLoad" loext:mime-type="image/png"/></draw:frame></text:p><text:p text:style-name="P1">The warnings section also shows in the encounter (point &amp; click) exam. Contact your MIE Implementer if you want it programmed on any encounter.</text:p><text:p text:style-name="P1"><draw:frame draw:style-name="fr1" draw:name="image2.jpg" text:anchor-type="as-char" svg:width="8.6772in" svg:height="5.3228in" draw:z-index="0"><draw:image xlink:href="Pictures/1000000000000341000001FF0557C97948108FC6.jpg" xlink:type="simple" xlink:show="embed" xlink:actuate="onLoad" loext:mime-type="image/jpeg"/></draw:frame></text:p><text:p text:style-name="P1">Drug interaction warnings and Allergy warnings will also appear in E-Meds module when adding an allergy/intolerance or prescribing a med, or in the patient’s medication history. <text:span text:style-name="T1">{{% system-name %}}</text:span> can generate a warning stating contraindications and duplicate therapies, so we encourage entering allergies for patients and current meds the patient is taking.</text:p><text:p text:style-name="P1"><text:span text:style-name="T1">{{% system-name %}}</text:span> currently imports the First DataBank (FDB) update files on a weekly basis on Saturday mornings at 2 am. MIE then does a complete dump and reload of our databases based on these files. At the end of this process, we update a table in the database that keeps track of changes in the database. A nightly job on each of the client servers checks for updates in the database file, and updates the rxdb database on the server from our “home” version of the database if necessary.</text:p><text:p text:style-name="P1">We do not “message” after updates these updates. However, we do have a message on the Drug Guide that you can see what the version is. The Drug Guide Search feature is usually found in the sidemenu tab named References, however in your particular <text:span text:style-name="T1">{{% system-name %}}</text:span> system, it could be found in the Omniscope side tab or in the E-Chart tab. The Drug Guide Search program is also found while prescribing in the e-meds module. Wherever your particular Drug Guide Search program is, when you get to that program you will see under the Drug Guide search field bar for example: <text:span text:style-name="T2">Drug database version: 2.400, last updated 2010-06-12 02:16:17</text:span></text:p><text:p text:style-name="P1">This shows the last time we have updated the Drug database (not the rxdb as a whole, it looks specifically only for updates called ‘FDB Update’) on the server box the system is looking at. This mainly gives MIE information to make sure the client is getting the updates we are putting out in our “home” base version. If there is a problem with the home base version for some reason (even if this is up to date), this will have an issue, but MIE would be alerted internally that there is an issue with the mainline not getting updated properly.</text:p><text:p text:style-name="P1">For more information on how to use the Drug Guide Search, please see our <text:a xlink:type="simple" xlink:href="https://docs.google.com/document/d/1yfB8xD-yey4VBd_Yzka0pkd_PGCMq8s9GmZHCCbZiLA" text:style-name="ListLabel_20_1" text:visited-style-name="ListLabel_20_1"><text:span text:style-name="T3">Drug Guide Search</text:span></text:a> help documentation.</text:p><text:p text:style-name="P1"><draw:frame draw:style-name="fr1" draw:name="image5.png" text:anchor-type="as-char" svg:width="8.7291in" svg:height="4.2083in" draw:z-index="0"><draw:image xlink:href="Pictures/100000000000034600000194CA745C51393E155E.png" xlink:type="simple" xlink:show="embed" xlink:actuate="onLoad" loext:mime-type="image/png"/></draw:frame></text:p><text:p text:style-name="P1">The warnings automatically sort and default to order by Severity. Guidelines are scripted rules that MIE can program for you based on specific things you want to be alerted for on your patients based on different criteria and conditions. Contact your MIE Implementer if you wish to have a scripted rule/guideline programmed for your practice/specialty.</text:p><text:p text:style-name="P1"><draw:frame draw:style-name="fr1" draw:name="Image1" text:anchor-type="as-char" svg:width="9.4374in" svg:height="5.4374in" draw:z-index="0"><draw:image xlink:href="Pictures/100000000000038A0000020A63F8B6A4131A498C.png" xlink:type="simple" xlink:show="embed" xlink:actuate="onLoad" loext:mime-type="image/png"/></draw:frame></text:p><text:p text:style-name="P1">Hovering your mouse over the <draw:frame draw:style-name="fr1" draw:name="image1.png" text:anchor-type="as-char" svg:width="0.0008in" svg:height="0.0161in" draw:z-index="0"><draw:image xlink:href="Pictures/1000020100000001000000014C77D75F6DC67A52.png" xlink:type="simple" xlink:show="embed" xlink:actuate="onLoad" loext:mime-type="image/png"/></draw:frame><text:s/>help icon will pop-up a monolog more detailed information about that specific warning/alert.</text:p><text:p text:style-name="P1"><draw:frame draw:style-name="fr1" draw:name="image6.png" text:anchor-type="as-char" svg:width="9.2189in" svg:height="2.9063in" draw:z-index="0"><draw:image xlink:href="Pictures/100000000000037500000117840E8BCF3ADF313F.png" xlink:type="simple" xlink:show="embed" xlink:actuate="onLoad" loext:mime-type="image/png"/></draw:frame></text:p><text:p text:style-name="P2">If a Drug interaction warning or Allergy warning appears in a patient’s chart while prescribing or documenting.</text:p><text:p text:style-name="P4">Dismiss Allergy/Medication Warnings</text:p><text:p text:style-name="P1">Based on your security permission in <text:span text:style-name="T1">{{% system-name %}}</text:span> , you may be able to dismiss warnings for the patient only or for all patients or not at all.</text:p><text:p text:style-name="P1"><draw:frame draw:style-name="fr1" draw:name="image8.png" text:anchor-type="as-char" svg:width="2.6874in" svg:height="1in" draw:z-index="0"><draw:image xlink:href="Pictures/100000000000010200000060C45D9D5AF95850EC.png" xlink:type="simple" xlink:show="embed" xlink:actuate="onLoad" loext:mime-type="image/png"/></draw:frame></text:p><text:p text:style-name="P1">Most practices give the nurses/MA’s the right to dismiss for ‘this patient’ and give the physician’s the higher security to dismiss ‘for all patients’.</text:p><text:p text:style-name="P1"><draw:frame draw:style-name="fr1" draw:name="Image2" text:anchor-type="as-char" svg:width="9.4374in" svg:height="5.4374in" draw:z-index="0"><draw:image xlink:href="Pictures/100000000000038A0000020A63F8B6A4131A498C.png" xlink:type="simple" xlink:show="embed" xlink:actuate="onLoad" loext:mime-type="image/png"/></draw:frame></text:p><text:p text:style-name="P1">MIE cannot hide or remove the warnings.  To be an e-prescribe system and per the guidelines, etc we are to generate these interactions and warnings.  These warnings are required. These warnings also display/print on the Med Sheet. The system is telling you a warning, contraindication, interaction or duplicate therapy.</text:p><text:p text:style-name="P1">If you wish to dismiss it, you would do the following steps (if you have security permission to do so).</text:p><text:p text:style-name="P1">Usually, the Physician has been set with security rights to dismiss all levels.  The physician can dismiss the warning for that specific patient only.  Or the physician can dismiss the specific warning for all patients via him or all users.</text:p><text:p text:style-name="P1"><draw:frame draw:style-name="fr1" draw:name="image11.jpg" text:anchor-type="as-char" svg:width="7.4374in" svg:height="3.4165in" draw:z-index="0"><draw:image xlink:href="Pictures/10000000000002CA000001488526CC8FDEEF52B4.jpg" xlink:type="simple" xlink:show="embed" xlink:actuate="onLoad" loext:mime-type="image/jpeg"/></draw:frame></text:p><text:p text:style-name="P1">Usually, the nurses have been set with security rights to dismiss warnings only for that specific patient only (doesn’t affect all other patients).</text:p><text:p text:style-name="P1">If the physician does decide to dismiss, there is a security setting to dismiss “this one time for this one patient” or for “all patients”.  (Usually nurse’s only can dismiss for that specific patient only.  Physician’s usually are the only ones with full security rights).</text:p><text:p text:style-name="P1"> If the physician dismisses a warning for “all patients’ they would only have to dismiss once and never see it generated again.  We discourage this because it really defeats the purpose of showing warnings and affects all other patients and the warning won’t pop-up again for any patient.</text:p><text:p text:style-name="P1">If you wish to dismiss, go into the specific patient’s chart and click the dismiss option link. This is how the physician or the nurse can dismiss the warning.</text:p><text:p text:style-name="P1">Warnings should only be dismissed by nurse’s or MD’s. The <text:span text:style-name="T1">Reason for Dismissing</text:span> field should be filled out for why you are dismissing the warning. It will accept free text, but it will also auto-complete and give you choices of previous entries of reasons why warnings were dismissed (it saves previous reasons for dismissing entries if a dismissing reason was typed in twice exactly the same).</text:p><text:p text:style-name="P1"><draw:frame draw:style-name="fr1" draw:name="Image3" text:anchor-type="as-char" svg:width="4.6146in" svg:height="2.552in" draw:z-index="0"><draw:image xlink:href="Pictures/10000000000001BB000000F5CA0B5C9044D46272.png" xlink:type="simple" xlink:show="embed" xlink:actuate="onLoad" loext:mime-type="image/png"/></draw:frame></text:p><text:p text:style-name="P2"><draw:frame draw:style-name="fr1" draw:name="image4.png" text:anchor-type="as-char" svg:width="8.9272in" svg:height="2.9583in" draw:z-index="0"><draw:image xlink:href="Pictures/10000000000003590000011CC3F8FC7FD761302E.png" xlink:type="simple" xlink:show="embed" xlink:actuate="onLoad" loext:mime-type="image/png"/></draw:frame></text:p><text:p text:style-name="P4">Dismiss Guideline Warnings</text:p><text:p text:style-name="P1">Based on your security permission in <text:span text:style-name="T1">{{% system-name %}}</text:span> , you may be able to dismiss warnings for the patient only or for all patients or not at all.</text:p><text:p text:style-name="P1"><draw:frame draw:style-name="fr1" draw:name="Image4" text:anchor-type="as-char" svg:width="2.6874in" svg:height="1in" draw:z-index="0"><draw:image xlink:href="Pictures/100000000000010200000060C45D9D5AF95850EC.png" xlink:type="simple" xlink:show="embed" xlink:actuate="onLoad" loext:mime-type="image/png"/></draw:frame></text:p><text:p text:style-name="P1">Dismissing Guideline alerts/warnings on a patient’s chart are different than dismissing drug/allergy warnings. You can dismiss from the warnings/alerts portlet, warnings chart tab, or warnings section from encounters.</text:p><text:p text:style-name="P1"><draw:frame draw:style-name="fr1" draw:name="Image5" text:anchor-type="as-char" svg:width="4.6146in" svg:height="2.552in" draw:z-index="0"><draw:image xlink:href="Pictures/10000000000001BB000000F5CA0B5C9044D46272.png" xlink:type="simple" xlink:show="embed" xlink:actuate="onLoad" loext:mime-type="image/png"/></draw:frame></text:p><text:p text:style-name="P1">Click the Dismiss if you wish to dismiss the guideline alert for a patient for any reason.</text:p><text:p text:style-name="P1"><draw:frame draw:style-name="fr1" draw:name="image10.jpg" text:anchor-type="as-char" svg:width="7in" svg:height="0.8752in" draw:z-index="0"><draw:image xlink:href="Pictures/10000000000002A000000054F2A5B69DE9139C5B.jpg" xlink:type="simple" xlink:show="embed" xlink:actuate="onLoad" loext:mime-type="image/jpeg"/></draw:frame></text:p><text:p text:style-name="P1">You then have to type in a reason for dismissing (make sure you are dismissing for only that patient and not all patients w/ that guideline warning/alert).</text:p><text:p text:style-name="P1"><draw:frame draw:style-name="fr1" draw:name="image7.jpg" text:anchor-type="as-char" svg:width="7in" svg:height="1.75in" draw:z-index="0"><draw:image xlink:href="Pictures/10000000000002A0000000A8003D248BF2AC9076.jpg" xlink:type="simple" xlink:show="embed" xlink:actuate="onLoad" loext:mime-type="image/jpeg"/></draw:frame></text:p><text:p text:style-name="P1">Resume Warning: Enter a date you want the Warning to reappear on the patient’s chart. This warning will reappear on the day selected/entered. The date is when you want the alert dismissed until.  So the alert will not display again until the date that is entered. Blank means never. Leaving this date blank and submitting the dismissal will mean the warning will never reappear for this patient.</text:p></office:text></office:body></office:document-content>